strudel/__init__.py
strudel/callbacks.py
strudel/main.py
strudel/utils.py
strudel_cli-0.1.1.dist-info/METADATA
strudel_cli-0.1.1.dist-info/WHEEL
strudel_cli-0.1.1.dist-info/entry_points.txt
strudel_cli-0.1.1.dist-info/licenses/LICENSE
strudel_cli-0.1.1.dist-info/RECORD
