Metadata-Version: 2.3
Name: strudel-cli
Version: 0.1.1
Summary: A command-line tool for bootstrapping web applications based on the STRUDEL Design System
Project-URL: Homepage, https://github.com/strudel-science/strudel-kit
Project-URL: Issues, https://github.com/strudel-science/strudel-kit/issues
Author-email: Cody O'Donnell <ctodonnell@lbl.gov>, Dan Gunter <dkgunter@lbl.gov>
License: License Agreement
License-File: LICENSE
Classifier: Development Status :: 3 - Alpha
Classifier: Intended Audience :: Science/Research
Classifier: Operating System :: OS Independent
Classifier: Programming Language :: Python :: 3
Classifier: Topic :: Scientific/Engineering
Classifier: Topic :: Software Development :: User Interfaces
Requires-Python: >=3.8
Requires-Dist: cookiecutter==2.6.0
Requires-Dist: rich==13.3.5
Requires-Dist: typer==0.12.1
